reno/__init__.py
reno/cache.py
reno/config.py
reno/create.py
reno/defaults.py
reno/formatter.py
reno/linter.py
reno/lister.py
reno/loader.py
reno/main.py
reno/report.py
reno/scanner.py
reno/semver.py
reno/setup_command.py
reno/sphinxext.py
reno/utils.py
reno/_exts/__init__.py
reno/_exts/show_reno_config.py
reno/tests/__init__.py
reno/tests/base.py
reno/tests/test_cache.py
reno/tests/test_config.py
reno/tests/test_create.py
reno/tests/test_exts.py
reno/tests/test_formatter.py
reno/tests/test_loader.py
reno/tests/test_scanner.py
reno/tests/test_semver.py
reno/tests/test_utils.py
reno-4.1.0.dist-info/AUTHORS
reno-4.1.0.dist-info/LICENSE
reno-4.1.0.dist-info/METADATA
reno-4.1.0.dist-info/WHEEL
reno-4.1.0.dist-info/entry_points.txt
reno-4.1.0.dist-info/pbr.json
reno-4.1.0.dist-info/top_level.txt
reno-4.1.0.dist-info/RECORD
